LICENSE
MANIFEST.in
README.md
pyproject.toml
setup.cfg
setup.py
betterFlatPages/DRF_urls.py
betterFlatPages/DRF_views.py
betterFlatPages/__init__.py
betterFlatPages/admin.py
betterFlatPages/apps.py
betterFlatPages/forms.py
betterFlatPages/models.py
betterFlatPages/tests.py
betterFlatPages/urls.py
betterFlatPages/views.py
betterFlatPages/migrations/0001_initial.py
betterFlatPages/migrations/__init__.py
betterFlatPages/migrations/__pycache__/0001_initial.cpython-310.pyc
betterFlatPages/migrations/__pycache__/__init__.cpython-310.pyc
betterFlatPages/templates/betterFlatPages/base.html
betterFlatPages/templates/betterFlatPages/default.html
django_betterFlatPages.egg-info/PKG-INFO
django_betterFlatPages.egg-info/SOURCES.txt
django_betterFlatPages.egg-info/dependency_links.txt
django_betterFlatPages.egg-info/requires.txt
django_betterFlatPages.egg-info/top_level.txt